feast_postgres/__init__.py
feast_postgres/postgres_config.py
feast_postgres/registry_store.py
feast_postgres/type_map.py
feast_postgres/utils.py
feast_postgres/offline_stores/__init__.py
feast_postgres/offline_stores/postgres.py
feast_postgres/offline_stores/postgres_source.py
feast_postgres/online_stores/__init__.py
feast_postgres/online_stores/postgres.py
feast_postgres-0.2.5.dist-info/LICENSE
feast_postgres-0.2.5.dist-info/METADATA
feast_postgres-0.2.5.dist-info/WHEEL
feast_postgres-0.2.5.dist-info/top_level.txt
feast_postgres-0.2.5.dist-info/RECORD
