Metadata-Version: 2.1
Name: feast-postgres
Version: 0.2.5
Summary: PostgreSQL registry, and online and offline store for Feast
Home-page: https://github.com/nossrannug/feast-postgres
Author: Gunnar Sv Sigurbjörnsson
Author-email: gunnar.sigurbjornsson@gmail.com
License: Apache License, Version 2.0
Project-URL: Bug Tracker, https://github.com/nossrannug/feast-postgres/issues
Keywords: feast featurestore postgres offlinestore onlinestore
Platform: UNKNOWN
Classifier: License :: OSI Approved :: Apache Software License
Classifier: Programming Language :: Python
Classifier: Programming Language :: Python :: 3
Classifier: Programming Language :: Python :: 3.7
Classifier: Programming Language :: Python :: 3.8
Classifier: Programming Language :: Python :: 3.9
Requires-Python: >=3.7.0
License-File: LICENSE
Requires-Dist: feast (==0.19.*)
Requires-Dist: psycopg2-binary (>=2.8.3)
Requires-Dist: pyarrow (>=2.0.0)
Provides-Extra: dev
Requires-Dist: flake8 ; extra == 'dev'
Requires-Dist: black (==21.10b0) ; extra == 'dev'
Requires-Dist: isort (>=5) ; extra == 'dev'
Requires-Dist: mypy (==0.790) ; extra == 'dev'
Requires-Dist: build (==0.7.0) ; extra == 'dev'
Requires-Dist: twine (==3.4.2) ; extra == 'dev'
Requires-Dist: pytest (>=6.0.0) ; extra == 'dev'
